{
  "patch": "May 1, 2009 Patch",
  "changes": "10.12.1",
  "id": "Evelynn",
  "name": "Evelynn",
  "title": "Agony's Embrace",
  "image": {
    "full": "Evelynn.png",
    "sprite": "champion0.png",
    "group": "champion",
    "x": 288,
    "y": 96,
    "w": 48,
    "h": 48
  },
  "resource": "Mana",
  "herotype": "Assassin",
  "alttype": "Mage",
  "rangetype": "Melee",
  "be_cost": 1350,
  "rp_cost": 585,
  "adaptivetype": "magic",
  "info": {
    "attack": 4,
    "defense": 2,
    "magic": 7,
    "difficulty": 10
  },
  "stats": {
    "hp": 572,
    "hpperlevel": 84,
    "mp": 315.6,
    "mpperlevel": 42,
    "movespeed": 335,
    "armor": 37,
    "armorperlevel": 3.5,
    "spellblock": 32.1,
    "spellblockperlevel": 1.25,
    "attackrange": 125,
    "hpregen": 8.5,
    "hpregenperlevel": 0.75,
    "mpregen": 8.108,
    "mpregenperlevel": 0.6,
    "crit": 0,
    "critperlevel": 0,
    "attackdamage": 61,
    "attackdamageperlevel": 3,
    "attackspeedperlevel": 2.1,
    "attackspeed": 0.667
  },
  "skills": {
    "i1": {
      "riotId": "",
      "name": "Demon Shade",
      "maxrank": 0,
      "targeting": "Passive",
      "image": {
        "full": "Evelynn_Passive.png",
        "sprite": "passive0.png",
        "group": "passive",
        "x": 288,
        "y": 96,
        "w": 48,
        "h": 48
      },
      "description": [
        "{{sbc|Innate:}} '''Evelynn''' gains ''Demon Shade'' after not performing actions that [[Stealth#Breaking_stealth|break stealth]] for 4 seconds. Taking damage from enemy {{tip|champion|champions}} or {{tip|turret|turrets}} ends ''Demon Shade'' immediately and puts it on a {{fd|1.5}} second {{tt|static cooldown|unaffected by cooldown reduction}}.",
        "{{sbc|Demon Shade:}} While below {{as|{{sti|health|{{passive progression/deprecated version|250 to 590}} {{as|(+ 250% AP)}} health}}}}, '''Evelynn''' {{tip|heal|heals}} herself for {{passive progression/deprecated version|15 to 75}} every second. From [[Experience (champion)|level]] 6 onward, ''Demon Shade'' also grants {{tip|camouflage}}."
      ],
      "notes": "* ''Demon Shade'' is placed on a {{fd|1.5}} second cooldown upon [[death|respawning]].\n* ''Demon Shade'' activates even if '''Evelynn''' is {{si|Recall|Recalling}}.\n* Whenever ''Demon Shade'' activates, a puff of purple smoke will briefly appear around her.\n** She will be spotted by an enemy she has no vision of but ''Demon Shade's'' stealth will not break.\n[[File:Evelynn_Spotted.png|thumb|left|'''Evelynn''' being {{tip|sight|revealed}} in ''Demon Shade'' ''(post 6)''.]]",
      "skillkey": "I",
      "skillid": "i1",
      "effects": []
    },
    "q1": {
      "riotId": "EvelynnQ",
      "name": "Hate Spike",
      "maxrank": 5,
      "cooldown": [
        8
      ],
      "cost": [
        40,
        45,
        50,
        55,
        60
      ],
      "costtype": "Mana",
      "targeting": "[[Direction-targeted|Direction]] / [[Auto-targeted|Auto]]",
      "target_range": 800,
      "image": {
        "full": "EvelynnQ.png",
        "sprite": "spell2.png",
        "group": "spell",
        "x": 384,
        "y": 144,
        "w": 48,
        "h": 48
      },
      "description": [
        "{{sbc|Active:}} '''Evelynn''' launches a dart in the target direction, dealing {{tip|magic damage|{{as|magic damage}}}} to the first enemy hit. Hitting a {{tip|monster}} refunds {{sti|cdr|50%}} of ''Hate Spike's'' cooldown.",
        "For the next 4 seconds, the enemy hit takes {{as|'''bonus''' magic damage}} from her next 3 [[basic attack]]s and abilities.",
        "''Hate Spike'' may be re-activated up to 3 times at no cost until the ability comes off cooldown.",
        "{{sbc|Recast:}} '''Evelynn''' unleashes a line of deadly spikes in the direction of her attack target if they are in range, dealing {{as|magic damage}} to all enemies struck. ''Hate Spike'' will first prioritize '''Evelynn's''' attack target, then the nearest enemy champion."
      ],
      "notes": "*Each cast counts as an ability activation for the purposes of on-cast effects such as {{nie|Spellblade}}, charging {{ii|Spellbinder}}, and stacking {{ai|Force Pulse|Kassadin}}.\n* ''Hate Spike'' prioritizes:\n*# The last champion '''Evelynn''' hit\n*# The last non-champion '''Evelynn''' hit\n*# The lowest-health champion\n*# The lowest-health non-champion\n* The dart applies {{tip|spell damage}} and the spikes deal {{tip|area damage}}.\n* ''Hate Spike'' is always cast from the original casting position.\n* Recasts can be buffered up to {{fd|0.5}} seconds before becoming castable.\n* '''Evelynn''' has {{fd|3.7}} seconds to use all of the recasts if she hits a non-monster, regardless of the ''Hate Spike's'' {{sti|cooldown}}.",
      "skillkey": "Q",
      "skillid": "q1",
      "costBurn": "40/45/50/55/60",
      "cooldownBurn": "8",
      "effects": [
        {
          "levelingtext": "{{st|Dart Damage|{{ap|30 to 50}} {{as|(+ 30% AP)}}}}",
          "str": "<ul><li><span class=\"blue\">Dart Damage</span>: <span><spell-span :list=\"['30','35','40','45','50']\" :spellrankindex=\"spellrankindex\"></spell-span> <span class=\"ap\">(+ 30% AP)</span></span></li></ul>",
          "vars": {
            "ratios": {},
            "progression": [],
            "ap_progressions": [
              [
                30,
                35,
                40,
                45,
                50
              ]
            ],
            "as_ratios": [
              {
                "player_total_ap": 0.3
              }
            ],
            "st_slices": [
              "Dart Damage",
              "<spell-span :list=\"['30','35','40','45','50']\" :spellrankindex=\"spellrankindex\"></spell-span> <span class=\"ap\">(+ 30% AP)</span>"
            ]
          },
          "subeffects": [
            {
              "index": 0,
              "ratios": {
                "base_damage": [
                  30,
                  35,
                  40,
                  45,
                  50
                ],
                "player_total_ap": 0.3
              },
              "title": "Dart Damage",
              "str": "<spell-span :list=\"['30','35','40','45','50']\" :spellrankindex=\"spellrankindex\"></spell-span> <span class=\"ap\">(+ 30% AP)</span>",
              "damage_type": "unknown"
            }
          ]
        },
        {
          "levelingtext": "{{st|Bonus Damage|{{ap|10 to 50}} {{as|(+ 25% AP)}}|Total Bonus Damage|{{ap|10*3 to 50*3}} {{as|(+ 75% AP)}}}}",
          "str": "<ul><li><span class=\"blue\">Bonus Damage</span>: <span><spell-span :list=\"['10','20','30','40','50']\" :spellrankindex=\"spellrankindex\"></spell-span> <span class=\"ap\">(+ 25% AP)</span></span></li><li><span class=\"blue\">Total Bonus Damage</span>: <span><spell-span :list=\"['30','60','90','120','150']\" :spellrankindex=\"spellrankindex\"></spell-span> <span class=\"ap\">(+ 75% AP)</span></span></li></ul>",
          "vars": {
            "ratios": {},
            "progression": [],
            "ap_progressions": [
              [
                10,
                20,
                30,
                40,
                50
              ],
              [
                30,
                60,
                90,
                120,
                150
              ]
            ],
            "as_ratios": [
              {
                "player_total_ap": 0.25
              },
              {
                "player_total_ap": 0.75
              }
            ],
            "st_slices": [
              "Bonus Damage",
              "<spell-span :list=\"['10','20','30','40','50']\" :spellrankindex=\"spellrankindex\"></spell-span> <span class=\"ap\">(+ 25% AP)</span>",
              "Total Bonus Damage",
              "<spell-span :list=\"['30','60','90','120','150']\" :spellrankindex=\"spellrankindex\"></spell-span> <span class=\"ap\">(+ 75% AP)</span>"
            ]
          },
          "subeffects": [
            {
              "index": 0,
              "ratios": {
                "base_damage": [
                  10,
                  20,
                  30,
                  40,
                  50
                ],
                "player_total_ap": 0.25
              },
              "title": "Bonus Damage",
              "str": "<spell-span :list=\"['10','20','30','40','50']\" :spellrankindex=\"spellrankindex\"></spell-span> <span class=\"ap\">(+ 25% AP)</span>",
              "damage_type": "unknown"
            },
            {
              "index": 1,
              "ratios": {
                "base_damage": [
                  30,
                  60,
                  90,
                  120,
                  150
                ],
                "player_total_ap": 0.25
              },
              "title": "Total Bonus Damage",
              "str": "<spell-span :list=\"['30','60','90','120','150']\" :spellrankindex=\"spellrankindex\"></spell-span> <span class=\"ap\">(+ 75% AP)</span>",
              "damage_type": "unknown"
            }
          ]
        },
        {
          "levelingtext": "{{st|Spike Damage|{{ap|30 to 50}} {{as|(+ 30% AP)}}|Maximum Damage|{{ap|30*3 to 50*3}} {{as|(+ 90% AP)}}|Total Damage|{{ap|30*4+10*3 to 50*4+50*3}} {{as|(+ 195% AP)}}}}",
          "str": "<ul><li><span class=\"blue\">Spike Damage</span>: <span><spell-span :list=\"['30','35','40','45','50']\" :spellrankindex=\"spellrankindex\"></spell-span> <span class=\"ap\">(+ 30% AP)</span></span></li><li><span class=\"blue\">Maximum Damage</span>: <span><spell-span :list=\"['90','105','120','135','150']\" :spellrankindex=\"spellrankindex\"></spell-span> <span class=\"ap\">(+ 90% AP)</span></span></li><li><span class=\"blue\">Total Damage</span>: <span><spell-span :list=\"['150','200','250','300','350']\" :spellrankindex=\"spellrankindex\"></spell-span> <span class=\"ap\">(+ 195% AP)</span></span></li></ul>",
          "vars": {
            "ratios": {},
            "progression": [],
            "ap_progressions": [
              [
                30,
                35,
                40,
                45,
                50
              ],
              [
                90,
                105,
                120,
                135,
                150
              ],
              [
                150,
                200,
                250,
                300,
                350
              ]
            ],
            "as_ratios": [
              {
                "player_total_ap": 0.3
              },
              {
                "player_total_ap": 0.9
              },
              {
                "player_total_ap": 1.95
              }
            ],
            "st_slices": [
              "Spike Damage",
              "<spell-span :list=\"['30','35','40','45','50']\" :spellrankindex=\"spellrankindex\"></spell-span> <span class=\"ap\">(+ 30% AP)</span>",
              "Maximum Damage",
              "<spell-span :list=\"['90','105','120','135','150']\" :spellrankindex=\"spellrankindex\"></spell-span> <span class=\"ap\">(+ 90% AP)</span>",
              "Total Damage",
              "<spell-span :list=\"['150','200','250','300','350']\" :spellrankindex=\"spellrankindex\"></spell-span> <span class=\"ap\">(+ 195% AP)</span>"
            ]
          },
          "subeffects": [
            {
              "index": 0,
              "ratios": {
                "base_damage": [
                  30,
                  35,
                  40,
                  45,
                  50
                ],
                "player_total_ap": 0.3
              },
              "title": "Spike Damage",
              "str": "<spell-span :list=\"['30','35','40','45','50']\" :spellrankindex=\"spellrankindex\"></spell-span> <span class=\"ap\">(+ 30% AP)</span>",
              "damage_type": "unknown"
            },
            {
              "index": 1,
              "ratios": {
                "base_damage": [
                  90,
                  105,
                  120,
                  135,
                  150
                ],
                "player_total_ap": 0.3
              },
              "title": "Maximum Damage",
              "str": "<spell-span :list=\"['90','105','120','135','150']\" :spellrankindex=\"spellrankindex\"></spell-span> <span class=\"ap\">(+ 90% AP)</span>",
              "damage_type": "unknown"
            },
            {
              "index": 2,
              "ratios": {
                "base_damage": [
                  150,
                  200,
                  250,
                  300,
                  350
                ],
                "player_total_ap": 0.3
              },
              "title": "Total Damage",
              "str": "<spell-span :list=\"['150','200','250','300','350']\" :spellrankindex=\"spellrankindex\"></spell-span> <span class=\"ap\">(+ 195% AP)</span>",
              "damage_type": "unknown"
            }
          ]
        }
      ]
    },
    "w1": {
      "riotId": "EvelynnW",
      "name": "Allure",
      "maxrank": 5,
      "cooldown": [
        15,
        14,
        13,
        12,
        11
      ],
      "cost": [
        60,
        70,
        80,
        90,
        100
      ],
      "costtype": "Mana",
      "targeting": "Unit",
      "target_range": "{{tip|cr|icononly = true}} {{ap|1200 to 1600}}",
      "image": {
        "full": "EvelynnW.png",
        "sprite": "spell2.png",
        "group": "spell",
        "x": 432,
        "y": 144,
        "w": 48,
        "h": 48
      },
      "description": [
        "{{sbc|Active:}} '''Evelynn''' ''curses'' the target enemy {{tip|champion}} or {{tip|monster}} for 5 seconds.",
        "'''Evelynn's''' next [[basic attack]] or [[champion ability|ability]] against the ''accursed'' ''expunges'' them, {{tip|slow|slowing}} them by 65%.",
        "''Expunging'' a target will refund ''Allure's'' {{as|{{sti|mana|mana cost}}}}. If the target is ''cursed'' for at least {{fd|2.5}} seconds she also {{tip|charm|charms}} them, as well as applying additional effects based on the target type.",
        "Against champions, the ''expunge'' also {{sti|magic penetration|{{as|reduces their magic resistance}}}} for 4 seconds.<br>Against monsters, the ''expunge'' deals {{as|'''bonus''' magic damage}} and the {{tip|charm}} lasts 2 seconds longer.",
        "''Casting Allure does not break {{ai|Demon Shade|Evelynn}}.''"
      ],
      "notes": "* The mark fully forming signifies the {{fd|2.5}} seconds have elapsed, allowing the target to be ''expunged''.\n** An enemy champion cursed by ''Allure'' is alarmed of her presence and after the mark has fully formed, an arrow will appear next to them pointing towards '''Evelynn's''' direction. This is visible to both teams.\n* The {{stil|magic penetration}} will be applied to the attack or ability that triggers it.\n* ''Allure's'' mark application on a target cannot be blocked by {{tip|spell shield}}.|yvideo       = Evelynn - W",
      "skillkey": "W",
      "skillid": "w1",
      "costBurn": "60/70/80/90/100",
      "cooldownBurn": "15/14/13/12/11",
      "effects": [
        {
          "levelingtext": "{{st|Disable Duration|{{ap|1 to 2}}|Monster Duration|{{ap|1+2 to 2+2}}}}",
          "str": "<ul><li><span class=\"blue\">Disable Duration</span>: <span><spell-span :list=\"['1','1.25','1.5','1.75','2']\" :spellrankindex=\"spellrankindex\"></spell-span></span></li><li><span class=\"blue\">Monster Duration</span>: <span><spell-span :list=\"['3','3.25','3.5','3.75','4']\" :spellrankindex=\"spellrankindex\"></spell-span></span></li></ul>",
          "vars": {
            "ratios": {},
            "progression": [],
            "ap_progressions": [
              [
                1,
                1.25,
                1.5,
                1.75,
                2
              ],
              [
                3,
                3.25,
                3.5,
                3.75,
                4
              ]
            ],
            "st_slices": [
              "Disable Duration",
              "<spell-span :list=\"['1','1.25','1.5','1.75','2']\" :spellrankindex=\"spellrankindex\"></spell-span>",
              "Monster Duration",
              "<spell-span :list=\"['3','3.25','3.5','3.75','4']\" :spellrankindex=\"spellrankindex\"></spell-span>"
            ]
          },
          "subeffects": [
            {
              "index": 0,
              "ratios": {
                "base_progression": [
                  1,
                  1.25,
                  1.5,
                  1.75,
                  2
                ]
              },
              "title": "Disable Duration",
              "str": "<spell-span :list=\"['1','1.25','1.5','1.75','2']\" :spellrankindex=\"spellrankindex\"></spell-span>",
              "damage_type": "none"
            },
            {
              "index": 1,
              "ratios": {
                "base_progression": [
                  3,
                  3.25,
                  3.5,
                  3.75,
                  4
                ]
              },
              "title": "Monster Duration",
              "str": "<spell-span :list=\"['3','3.25','3.5','3.75','4']\" :spellrankindex=\"spellrankindex\"></spell-span>",
              "damage_type": "none"
            }
          ]
        },
        {
          "levelingtext": "{{st|Magic Resistance Reduction|{{as|{{ap|25 to 35}}%|magic resistance}}}}{{st|Bonus Magic Damage|{{ap|250 to 450}} {{as|(+ 60% AP)}}}}",
          "str": "<ul><li><span class=\"blue\">Magic Resistance Reduction</span>: <span><span class=\"magic-resistance\"><spell-span :list=\"['25','27.5','30','32.5','35']\" :spellrankindex=\"spellrankindex\"></spell-span>%</span></span></li></ul><ul><li><span class=\"blue\">Bonus Magic Damage</span>: <span><spell-span :list=\"['250','300','350','400','450']\" :spellrankindex=\"spellrankindex\"></spell-span> <span class=\"ap\">(+ 60% AP)</span></span></li></ul>",
          "vars": {
            "ratios": {},
            "progression": [],
            "ap_progressions": [
              [
                25,
                27.5,
                30,
                32.5,
                35
              ],
              null
            ],
            "as_ratios": [
              {
                "player_total_ap": 0.6
              },
              {
                "player_total_unknown": [
                  2.5,
                  3,
                  3.5,
                  4,
                  4.5
                ]
              }
            ],
            "st_slices": [
              "Magic Resistance Reduction",
              "<span class=\"magic-resistance\"><spell-span :list=\"['25','27.5','30','32.5','35']\" :spellrankindex=\"spellrankindex\"></spell-span>%</span>"
            ]
          },
          "subeffects": [
            {
              "index": 0,
              "ratios": {
                "base_progression": [
                  25,
                  27.5,
                  30,
                  32.5,
                  35
                ],
                "player_total_ap": 0.6,
                "player_total_unknown": [
                  2.5,
                  3,
                  3.5,
                  4,
                  4.5
                ]
              },
              "title": "Magic Resistance Reduction",
              "str": "<span class=\"magic-resistance\"><spell-span :list=\"['25','27.5','30','32.5','35']\" :spellrankindex=\"spellrankindex\"></spell-span>%</span>",
              "damage_type": "none"
            }
          ]
        }
      ]
    },
    "r1": {
      "riotId": "EvelynnR",
      "name": "Last Caress",
      "maxrank": 3,
      "cooldown": [
        140,
        110,
        80
      ],
      "cost": [
        100,
        100,
        100
      ],
      "costtype": "Mana",
      "targeting": "Direction",
      "image": {
        "full": "EvelynnR.png",
        "sprite": "spell3.png",
        "group": "spell",
        "x": 48,
        "y": 0,
        "w": 48,
        "h": 48
      },
      "description": [
        "{{sbc|Active:}} '''Evelynn''' becomes {{tip|untargetable}} as she reveals her true form to all enemies in front of her, before {{tip|blink|blinking}} back 700 units.",
        "Enemies caught in her reveal are devastated, taking {{as|magic damage}}, with enemies below {{as|{{sti|health|30% of their '''maximum''' health}}}} receiving [[File:Critical_magic_strike_icon.png|20px|link=]] {{tt|140% '''bonus''' damage|cosmetic critical strike}}."
      ],
      "notes": "* ''Last Caress'' can be buffered during {{ai|Empowered Whiplash|Evelynn}}.\n* The casting input controls the direction ''Last Caress' '' damage is dealt from, with the movement automatically happening in the reverse direction.\n* Enemy {{tip|champion|champions}} below the {{as|maximum health}} threshold are {{Color|pink|'''marked'''}} for '''Evelynn''', indicating the bonus damage opportunity.\n* The screen will direct to '''Evelynn's''' position after she {{tip|blink|blinks}}.",
      "skillkey": "R",
      "skillid": "r1",
      "costBurn": "100",
      "cooldownBurn": "140/110/80",
      "effects": [
        {
          "levelingtext": "{{st|Magic Damage|{{ap|125 to 375}} {{as|(+ 75% AP)}}|Empowered Damage|{{ap|125*2.4 to 375*2.4}} {{as|(+ {{ap|75*2.4}}% AP)}}}}",
          "str": "<ul><li><span class=\"blue\">Magic Damage</span>: <span><spell-span :list=\"['125','187.5','250','312.5','375']\" :spellrankindex=\"spellrankindex\"></spell-span> <span class=\"ap\">(+ 75% AP)</span></span></li><li><span class=\"blue\">Empowered Damage</span>: <span><spell-span :list=\"['300','450','600','750','900']\" :spellrankindex=\"spellrankindex\"></spell-span> <span class=\"ap\">(+ <spell-span :list=\"['180']\" :spellrankindex=\"spellrankindex\"></spell-span>% AP)</span></span></li></ul>",
          "vars": {
            "ratios": {},
            "progression": [],
            "ap_progressions": [
              [
                125,
                187.5,
                250,
                312.5,
                375
              ],
              [
                300,
                450,
                600,
                750,
                900
              ],
              null
            ],
            "as_ratios": [
              {
                "player_total_ap": 0.75
              },
              {
                "player_total_ap": [
                  1.8
                ]
              }
            ],
            "st_slices": [
              "Magic Damage",
              "<spell-span :list=\"['125','187.5','250','312.5','375']\" :spellrankindex=\"spellrankindex\"></spell-span> <span class=\"ap\">(+ 75% AP)</span>",
              "Empowered Damage",
              "<spell-span :list=\"['300','450','600','750','900']\" :spellrankindex=\"spellrankindex\"></spell-span> <span class=\"ap\">(+ <spell-span :list=\"['180']\" :spellrankindex=\"spellrankindex\"></spell-span>% AP)</span>"
            ]
          },
          "subeffects": [
            {
              "index": 0,
              "ratios": {
                "base_damage": [
                  125,
                  187.5,
                  250,
                  312.5,
                  375
                ],
                "player_total_ap": 0.75
              },
              "title": "Magic Damage",
              "str": "<spell-span :list=\"['125','187.5','250','312.5','375']\" :spellrankindex=\"spellrankindex\"></spell-span> <span class=\"ap\">(+ 75% AP)</span>",
              "damage_type": "magic"
            },
            {
              "index": 1,
              "ratios": {
                "base_damage": [
                  300,
                  450,
                  600,
                  750,
                  900
                ],
                "player_total_ap": 0.75
              },
              "title": "Empowered Damage",
              "str": "<spell-span :list=\"['300','450','600','750','900']\" :spellrankindex=\"spellrankindex\"></spell-span> <span class=\"ap\">(+ <spell-span :list=\"['180']\" :spellrankindex=\"spellrankindex\"></spell-span>% AP)</span>",
              "damage_type": "unknown"
            }
          ]
        }
      ]
    }
  }
}