{
  "patch": "V10.25",
  "changes": "11.15.1",
  "id": "Rell",
  "name": "Rell",
  "title": "the Iron Maiden",
  "image": {
    "full": "Rell.png",
    "sprite": "champion3.png",
    "group": "champion",
    "x": 336,
    "y": 0,
    "w": 48,
    "h": 48
  },
  "resource": "Mana",
  "herotype": "Tank",
  "alttype": "",
  "rangetype": "Melee",
  "be_cost": 6300,
  "rp_cost": 975,
  "adaptivetype": "magic",
  "info": {
    "attack": 0,
    "defense": 0,
    "magic": 0,
    "difficulty": 0
  },
  "stats": {
    "hp": 540,
    "hpperlevel": 90,
    "mp": 350,
    "mpperlevel": 45,
    "movespeed": 335,
    "armor": 32,
    "armorperlevel": 3,
    "spellblock": 32.1,
    "spellblockperlevel": 1.25,
    "attackrange": 175,
    "hpregen": 7,
    "hpregenperlevel": 0.55,
    "mpregen": 6,
    "mpregenperlevel": 0.35,
    "crit": 0,
    "critperlevel": 0,
    "attackdamage": 55,
    "attackdamageperlevel": 3,
    "attackspeedperlevel": 2,
    "attackspeed": 0.55
  },
  "skills": {
    "i1": {
      "riotId": "",
      "name": "Break_the_Mold",
      "maxrank": 0,
      "cooldown": "",
      "targeting": "Passive",
      "image": {
        "full": "RellP.DarkSupport.png",
        "sprite": "passive3.png",
        "group": "passive",
        "x": 336,
        "y": 0,
        "w": 48,
        "h": 48
      },
      "description": [
        "{{sbc|Innate:}} '''Rell's''' [[basic attack]]s deal {{as|{{pp|8 to 16}}|magic damage}} {{as|'''bonus''' magic damage}} and reduce the target's {{sti|armor penetration|{{as|armor}}}} and {{sti|magic penetration|{{as|magic resistance}}}} by 10% for 4 seconds, refreshing on subsequent attacks against them. Basic attacks against enemy champions will refresh the duration for all nearby afflicted enemies.",
        "'''Rell''' gains {{sti|{{as|'''bonus''' armor}}}} and {{sti|{{as|'''bonus''' magic resistance}}}} equal to the sum of the resistances reduced from all afflicted enemies, respectively, and ''Break the Mold's'' '''bonus''' damage is increased equal to the sum of the resistances reduced from the target.",
        "''Break the Mold'' will reduce the target's {{as|armor}} and {{as|magic resistance}} by a minimum of {{pp|5 to 12 for 8|1;3;5;8;10;12;15;17}}, or {{pp|0.5 to 2 for 3|1;2;13}} versus {{tip|minions}}.",
        "'''Rell's''' {{tip|attack windup}} is reduced{{ft|by {{pp|100-(0.42 to 0.39)/0.42*100|key=%}}.|to {{pp|(0.42 to 0.39)/(0.55/{{ccd|Rell|as_base}})*100|round=3|key=%}}.}}"
      ],
      "descriptionHtml": "<span class=\"sbc\">Innate:</span> <b>Rell's</b> <a class=\"effect link\" title=\"basic attack\">basic attack</a>s deal <span class=\"magic-damage\"><HtmlTooltip class=\"blue link\">8undefined − 16undefined (based on level)<template #content>Values: 8, 8.471, 8.941, 9.412, 9.882, 10.353, 10.824, 11.294, 11.765, 12.235, 12.706, 13.176, 13.647, 14.118, 14.588, 15.059, 15.529, 16<br>At levels: 1, 2, 3, 4, 5, 6, 7, 8, 9, 10, 11, 12, 13, 14, 15, 16, 17, 18</template></HtmlTooltip></span> <span class=\"magic-damage\"><b>bonus</b> magic damage</span> and reduce the target's <span><span class=\"armor\">armor</span></span> and <span><span class=\"magic-resist\">magic resistance</span></span> by 10% for 4 seconds, refreshing on subsequent attacks against them. Basic attacks against enemy champions will refresh the duration for all nearby afflicted enemies.<br /><b>Rell</b> gains <span><span class=\"armor\"><b>bonus</b> armor</span></span> and <span><span class=\"magic-resist\"><b>bonus</b> magic resistance</span></span> equal to the sum of the resistances reduced from all afflicted enemies, respectively, and <i>Break the Mold's</i> <b>bonus</b> damage is increased equal to the sum of the resistances reduced from the target.<br /><i>Break the Mold</i> will reduce the target's <span class=\"armor\">armor</span> and <span class=\"magic-resist\">magic resistance</span> by a minimum of <span class=\"title-tooltip\" title=\"\">1;3;5;8;10;12;15;17 ‒ undefined</span>, or <span class=\"title-tooltip\" title=\"\">1;2;13 ‒ undefined</span> versus <HtmlTooltip class=\"blue link\">minions<template #content><div><h4>Lane Minions<hr></h4><p>A unit that is <i>slowed</i> has reduced movement speed for the duration.<br><br>Duration reduced by <b>Tenacity</b>.<br>Strength is reduced by <b>Slow resist</b>.</p></div></template></HtmlTooltip>.<br /><b>Rell's</b> <HtmlTooltip class=\"blue link\">attack windup<template #content><div><h4>attack windup<hr></h4><p>Description for keyword attack windup</p></div></template></HtmlTooltip> is reduced<label class=\"ft\"><input type=\"checkbox\"><span class=\"flipText1\">「&nbsp;by <simple-tooltip class=\"red\" dname=\"pp 100-(0.42 to 0.39)/0.42*100 key=%\">Error: SyntaxError: Unexpected end of input</simple-tooltip>.&nbsp;」</span><span class=\"flipText2\">「&nbsp;to <simple-tooltip class=\"red\" dname=\"pp (0.42 to 0.39)/(0.55/<simple-tooltip class=\"capture-unknown\" dname=\"ccd / Rell / as_base\">Unknown value: ccd / Rell / as_base</simple-tooltip>)*100 round=3 key=%\">Error: SyntaxError: Unexpected end of input</simple-tooltip>.&nbsp;」</span></label>",
      "leveling": [],
      "notes": "* The resistances are stolen after the damage from the triggering attack is calculated, meaning only subsequent attacks will benefit from the reduction.\n* '''Rell's''' [[buff]] accumulates enemies with ''Break the Mold's'' [[debuff]] and she will consequently lose a portion of the bonus resistances gained as afflicted enemies die. This is contrary to other effects described as \"thefts\" (e.g. {{ai|Seismic Shard|Malphite}} and {{ai|Subjugate|Trundle}}) that are implemented by granting a buff to the caster that is proportionate, though independent, to the debuff applied to the target (i.e. in those instances, each persists for the full duration regardless).",
      "skillkey": "I",
      "skillid": "i1",
      "effects": []
    },
    "q1": {
      "riotId": "RellQ",
      "name": "Shattering_Strike",
      "maxrank": 5,
      "cooldown": [
        9,
        8,
        7,
        6,
        5
      ],
      "cost": 50,
      "costtype": "mana",
      "targeting": "Direction",
      "image": {
        "full": "RellQ.png",
        "sprite": "spell10.png",
        "group": "spell",
        "x": 192,
        "y": 0,
        "w": 48,
        "h": 48
      },
      "description": [
        "{{sbc|Active:}} '''Rell''' thrusts her lance in the target direction, completely destroying damage-mitigating {{tip|shield|shields}} of enemies hit before dealing them {{as|magic damage}}, reduced to 50% against enemies beyond the first. The first enemy hit is also afflicted with {{ai|Break the Mold|Rell}}.",
        "If '''Rell''' is tethered with {{ai|Attract and Repel|Rell}}, she and the bound ally {{tip|heal}} for each enemy champion hit."
      ],
      "descriptionHtml": "<span class=\"sbc\">Active:</span> <b>Rell</b> thrusts her lance in the target direction, completely destroying damage-mitigating <HtmlTooltip class=\"blue link\">shields<template #content><div><h4>shield<hr></h4><p>Description for keyword shield</p></div></template></HtmlTooltip> of enemies hit before dealing them <span class=\"magic-damage\">magic damage</span>, reduced to 50% against enemies beyond the first. The first enemy hit is also afflicted with <span class=\"ai\">Rell's Break the Mold</span>.<br />If <b>Rell</b> is tethered with <span class=\"ai\">Rell's Attract and Repel</span>, she and the bound ally <HtmlTooltip class=\"blue link\">heal<template #content><div><h4>Healing<hr></h4><p><b>Healing</b> restores some of the user or the target's <span class=\"health\">current health</span> directly.<br><br>Healing can be reduced by <b>Grievous Wounds</b>.</p></div></template></HtmlTooltip> for each enemy champion hit.",
      "leveling": [
        "{{st|Magic Damage|{{ap|70 to 210}} {{as|(+ 50% AP)}}|Secondary Damage|{{ap|70*0.5 to 210*0.5}} {{as|(+ 25% AP)}}}}",
        "{{st|Heal Per Champion|{{ap|10 to 30}} {{as|(+ 30% AP)}} {{as|(+ 5% of '''missing''' health)}}}}"
      ],
      "notes": "{{Effect at cast time end}}\n* '''Rell''' is {{tip|lockout|locked out}} of moving, attacking, and casting any other ability except {{ai|Attract and Repel|Rell}} for {{fd|0.35}} seconds after ''Shattering Strike'' is cast.\n** Casting {{ai|Attract and Repel|Rell}} will cancel ''Shattering Strike''. The ability will not go on cooldown but will still expend {{as|mana}}.{{bug|2}}\n* ''Shattering Strike'', while binded to an ally, will grant the {{tip|heal}} from hitting {{tip|clone|clones}} as well.",
      "skillkey": "Q",
      "skillid": "q1",
      "effects": [
        {
          "str": "<ul class=\"st\"><li><span class=\"blue\">Magic Damage</span>: <span><SpellSpan :list=\"[70,105,140,175,210]\"></SpellSpan> <span class=\"ap\">(+ 50% AP)</span></span></li><li><span class=\"blue\">Secondary Damage</span>: <span><SpellSpan :list=\"[35,52.5,70,87.5,105]\"></SpellSpan> <span class=\"ap\">(+ 25% AP)</span></span></li></ul>",
          "vars": {
            "as_ratios": [
              {
                "player_total_ap": 0.5
              },
              {
                "player_total_ap": 0.25
              }
            ],
            "st_slices": [
              [
                "Magic Damage",
                "<SpellSpan :list=\"[70,105,140,175,210]\"></SpellSpan> <span class=\"ap\">(+ 50% AP)</span>",
                "Secondary Damage",
                "<SpellSpan :list=\"[35,52.5,70,87.5,105]\"></SpellSpan> <span class=\"ap\">(+ 25% AP)</span>"
              ]
            ],
            "ap_progressions": [
              [
                70,
                105,
                140,
                175,
                210
              ],
              [
                35,
                52.5,
                70,
                87.5,
                105
              ]
            ]
          },
          "subeffects": [
            {
              "index": 0,
              "title": "Magic Damage",
              "damage_type": "magic",
              "ratios": {
                "base_damage": [
                  70,
                  105,
                  140,
                  175,
                  210
                ],
                "player_total_ap": 0.25
              }
            }
          ]
        },
        {
          "str": "<ul class=\"st\"><li><span class=\"blue\">Heal Per Champion</span>: <span><SpellSpan :list=\"[10,15,20,25,30]\"></SpellSpan> <span class=\"ap\">(+ 30% AP)</span> <span class=\"health\">(+ 5% of <b>missing</b> health)</span></span></li></ul>",
          "vars": {
            "as_ratios": [
              {
                "player_total_ap": 0.3
              },
              {
                "player_missing_hp": 0.05
              }
            ],
            "st_slices": [
              [
                "Heal Per Champion",
                "<SpellSpan :list=\"[10,15,20,25,30]\"></SpellSpan> <span class=\"ap\">(+ 30% AP)</span> <span class=\"health\">(+ 5% of <b>missing</b> health)</span>"
              ]
            ],
            "ap_progressions": [
              [
                10,
                15,
                20,
                25,
                30
              ]
            ]
          },
          "subeffects": [
            {
              "index": 0,
              "title": "Heal Per Champion",
              "damage_type": "magic",
              "ratios": {
                "base_damage": [
                  10,
                  15,
                  20,
                  25,
                  30
                ],
                "player_total_ap": 0.3,
                "player_missing_hp": 0.05
              }
            }
          ]
        }
      ]
    },
    "w1": {
      "riotId": "RellW_Dismount",
      "name": "Ferromancy:_Crash_Down",
      "maxrank": 5,
      "cooldown": 11,
      "cost": 40,
      "costtype": "Mana",
      "targeting": "Location",
      "image": {
        "full": "RellW_Dismount.png",
        "sprite": "spell10.png",
        "group": "spell",
        "x": 240,
        "y": 0,
        "w": 48,
        "h": 48
      },
      "description": [
        "{{sbc|Passive:}} While mounted, '''Rell''' gains {{as|{{pp|key=%|5 to 15 for 11|1;7 to 16}} {{sti|'''bonus''' movement speed}}}}, which is only {{pp|key=%|20 to 40|formula=20% + (40% - 20%) / 17 * (level - 1)}} as effective for 3 seconds when she takes damage from non-{{tip|minions}} and is removed for 4 seconds when she becomes {{tip|immobilize|immobilized}} or {{tip|polymorph|polymorphed}}.",
        "{{sbc|Active:}} '''Rell''' {{tip|dash|leaps}} to the target location over the cast time, transforming her mount into durable armor and upon landing dealing {{as|magic damage}} to nearby enemies and {{tip|airborne|knocking them up}} for 1 second. '''Rell''' keeps {{tip|dash|sliding}} forward another {{tt|300 units|Estimated}} over {{tt|{{fd|0.5}} seconds|Estimated}}, though not through terrain, affecting further enemies along her path.",
        "While dismounted, she gains the ability to cast {{ai|Ferromancy: Mount Up|Rell}}. '''Rell''' will automatically revert to being mounted without casting the ability and reset {{ais|Ferromancy: Mount Up|Rell}} cooldown upon completing a {{si|Recall}} channel or respawning.",
        "''This ability can only be cast while mounted. '''Rell''' can cast {{ai|Attract and Repel|Rell}} and {{ai|Magnet Storm|Rell}} during the leap, and is not considered to be dismounted until after the leap ends.''"
      ],
      "descriptionHtml": "<span class=\"sbc\">Passive:</span> While mounted, <b>Rell</b> gains <span class=\"movement-speed\"><span class=\"title-tooltip\" title=\"\">1;7 to 16 ‒ undefined</span> <span><b>bonus</b> movement speed</span></span>, which is only <HtmlTooltip class=\"blue link\">20% − 40% (based on level)<template #content>Values: 20, 21.176, 22.353, 23.529, 24.706, 25.882, 27.059, 28.235, 29.412, 30.588, 31.765, 32.941, 34.118, 35.294, 36.471, 37.647, 38.824, 40<br>At levels: 1, 2, 3, 4, 5, 6, 7, 8, 9, 10, 11, 12, 13, 14, 15, 16, 17, 18</template></HtmlTooltip> as effective for 3 seconds when she takes damage from non-<HtmlTooltip class=\"blue link\">minions<template #content><div><h4>Lane Minions<hr></h4><p>A unit that is <i>slowed</i> has reduced movement speed for the duration.<br><br>Duration reduced by <b>Tenacity</b>.<br>Strength is reduced by <b>Slow resist</b>.</p></div></template></HtmlTooltip> and is removed for 4 seconds when she becomes <HtmlTooltip class=\"blue link\">immobilized<template #content><div><h4>immobilize<hr></h4><p>Description for keyword immobilize</p></div></template></HtmlTooltip> or <HtmlTooltip class=\"blue link\">polymorphed<template #content><div><h4>polymorph<hr></h4><p>Description for keyword polymorph</p></div></template></HtmlTooltip>.<br /><span class=\"sbc\">Active:</span> <b>Rell</b> <HtmlTooltip class=\"blue link\">leaps<template #content><div><h4>dash<hr></h4><p>Description for keyword dash</p></div></template></HtmlTooltip> to the target location over the cast time, transforming her mount into durable armor and upon landing dealing <span class=\"magic-damage\">magic damage</span> to nearby enemies and <HtmlTooltip class=\"blue link\">knocking them up<template #content><div><h4>airborne<hr></h4><p>Description for keyword airborne</p></div></template></HtmlTooltip> for 1 second. <b>Rell</b> keeps <HtmlTooltip class=\"blue link\">sliding<template #content><div><h4>dash<hr></h4><p>Description for keyword dash</p></div></template></HtmlTooltip> forward another <span class=\"title-tooltip\" title=\"Estimated\">300 units</span> over <span class=\"title-tooltip\" title=\"Estimated\"><span style=\"font-variant-numeric: tabular-nums;\">0.5</span> seconds</span>, though not through terrain, affecting further enemies along her path.<br />While dismounted, she gains the ability to cast <span class=\"ai\">Rell's Ferromancy: Mount Up</span>. <b>Rell</b> will automatically revert to being mounted without casting the ability and reset <span class=\"ais\">Rell's Ferromancy: Mount Up</span> cooldown upon completing a <simple-tooltip dname=\"Recall\" data-spellkey=\"Recall\">Recall</simple-tooltip> channel or respawning.<br /><i>This ability can only be cast while mounted. <b>Rell</b> can cast <span class=\"ai\">Rell's Attract and Repel</span> and <span class=\"ai\">Rell's Magnet Storm</span> during the leap, and is not considered to be dismounted until after the leap ends.</i>",
      "leveling": [
        "{{st|Magic Damage|{{ap|70 to 210}} {{as|(+ 60% AP)}}}}"
      ],
      "notes": "* '''Rell''' {{tip|dash|slides}} between 250 and 350 units in testing, depending on how far the spell was targeted. It is not known where this is intended.\n* If '''Rell''' dashes before a wall on the map, the slide will cover a shorter distance to the terrain over the same time, moving slower.\n** {{pending for test}} Interaction with player-made walls.\n* The following table refers for interactions while '''Rell''' is dashing/in cast time:\n{{ct|attack=false|move=false|cast={{ai|Q|Rell}} is disabled. {{ai|E|Rell}} and {{ai|R|Rell}} are usable.|items=true,,,false,false,,,false|spells=true,false,false,false,false|interrupts=death}}",
      "skillkey": "W",
      "skillid": "w1",
      "effects": [
        {
          "str": "<ul class=\"st\"><li><span class=\"blue\">Magic Damage</span>: <span><SpellSpan :list=\"[70,105,140,175,210]\"></SpellSpan> <span class=\"ap\">(+ 60% AP)</span></span></li></ul>",
          "vars": {
            "as_ratios": [
              {
                "player_total_ap": 0.6
              }
            ],
            "st_slices": [
              [
                "Magic Damage",
                "<SpellSpan :list=\"[70,105,140,175,210]\"></SpellSpan> <span class=\"ap\">(+ 60% AP)</span>"
              ]
            ],
            "ap_progressions": [
              [
                70,
                105,
                140,
                175,
                210
              ]
            ]
          },
          "subeffects": [
            {
              "index": 0,
              "title": "Magic Damage",
              "damage_type": "magic",
              "ratios": {
                "base_damage": [
                  70,
                  105,
                  140,
                  175,
                  210
                ],
                "player_total_ap": 0.6
              }
            }
          ]
        }
      ]
    },
    "w2": {
      "riotId": "RellW_Dismount",
      "name": "Ferromancy:_Mount_Up",
      "maxrank": 5,
      "cooldown": 11,
      "cost": 0,
      "targeting": "Auto",
      "image": {
        "full": "RellW_Dismount.png",
        "sprite": "spell10.png",
        "group": "spell",
        "x": 240,
        "y": 0,
        "w": 48,
        "h": 48
      },
      "description": [
        "{{sbc|Passive:}} While dismounted, '''Rell''' gains {{sti|{{as|10% '''bonus''' armor}}}} and {{sti|{{as|10% '''bonus''' magic resistance}}}} and a {{tip|shield}} that lasts until destroyed or casting {{ai|Ferromancy: Mount Up|Rell}}, but her {{as|'''base''' movement speed}} is modified to {{as|250|ms}}, and she has a movement speed cap of {{pp|key=|290 to 400|formula=290 + (110) / 17 * (level - 1)}}.",
        "{{sbc|Active:}} '''Rell''' transforms her armor into a mount, gaining {{as|15% '''bonus''' movement speed}} for {{fd|3.5}} seconds, increased to an amount when moving towards enemy champions.",
        "'''Rell's''' next basic attack during this time gains {{sti|100 '''bonus''' attack range}} and consumes the {{as|'''bonus''' movement speed}} to have a {{fd|0.2}}-second cast time during which she {{tip|dash|charges}} at the target's location. At the end of the dash or upon premature collision, she deals them {{as|'''bonus''' magic damage}}, {{tip|stun|stuns}} them for 1 second, and {{tip|airborne|flings}} them 150 units over herself.",
        "''Ferromancy: Mount Up'' {{tip|basic attack reset|resets}} '''Rell's''' basic attack timer.",
        "While mounted, she gains the ability to cast {{ai|Ferromancy: Crash Down|Rell}}."
      ],
      "descriptionHtml": "<span class=\"sbc\">Passive:</span> While dismounted, <b>Rell</b> gains <span><span class=\"armor\">10% <b>bonus</b> armor</span></span> and <span><span class=\"magic-resist\">10% <b>bonus</b> magic resistance</span></span> and a <HtmlTooltip class=\"blue link\">shield<template #content><div><h4>shield<hr></h4><p>Description for keyword shield</p></div></template></HtmlTooltip> that lasts until destroyed or casting <span class=\"ai\">Rell's Ferromancy: Mount Up</span>, but her <span class=\"movement-speed\"><b>base</b> movement speed</span> is modified to <span class=\"ms\">250</span>, and she has a movement speed cap of <HtmlTooltip class=\"blue link\">290 − 400 (based on level)<template #content>Values: 290, 296.471, 302.941, 309.412, 315.882, 322.353, 328.824, 335.294, 341.765, 348.235, 354.706, 361.176, 367.647, 374.118, 380.588, 387.059, 393.529, 400<br>At levels: 1, 2, 3, 4, 5, 6, 7, 8, 9, 10, 11, 12, 13, 14, 15, 16, 17, 18</template></HtmlTooltip>.<br /><span class=\"sbc\">Active:</span> <b>Rell</b> transforms her armor into a mount, gaining <span class=\"movement-speed\">15% <b>bonus</b> movement speed</span> for <span style=\"font-variant-numeric: tabular-nums;\">3.5</span> seconds, increased to an amount when moving towards enemy champions.<br /><b>Rell's</b> next basic attack during this time gains <span>100 <b>bonus</b> attack range</span> and consumes the <span class=\"movement-speed\"><b>bonus</b> movement speed</span> to have a <span style=\"font-variant-numeric: tabular-nums;\">0.2</span>-second cast time during which she <HtmlTooltip class=\"blue link\">charges<template #content><div><h4>dash<hr></h4><p>Description for keyword dash</p></div></template></HtmlTooltip> at the target's location. At the end of the dash or upon premature collision, she deals them <span class=\"magic-damage\"><b>bonus</b> magic damage</span>, <HtmlTooltip class=\"blue link\">stuns<template #content><div><h4>Stun<hr></h4><p>Unit is unable to control its movement, declare attacks, cast abilities, activate items, or use the summoner <b>Flash</b> and <b>Teleport</b> for the duration.<br><br>\nInterrupts all channeled and charged abilities<br>\nDuration reduced by <b>Tenacity</b>.<br>\nResisted by Spell and Crowd Control Immunity.<br>\nRemoved by <b>Cleanse</b>, <b>Quicksilver</b>, <b>Mikael's Crucible</b><br></p></div></template></HtmlTooltip> them for 1 second, and <HtmlTooltip class=\"blue link\">flings<template #content><div><h4>airborne<hr></h4><p>Description for keyword airborne</p></div></template></HtmlTooltip> them 150 units over herself.<br /><i>Ferromancy: Mount Up</i> <HtmlTooltip class=\"blue link\">resets<template #content><div><h4>basic attack reset<hr></h4><p>Description for keyword basic attack reset</p></div></template></HtmlTooltip> <b>Rell's</b> basic attack timer.<br />While mounted, she gains the ability to cast <span class=\"ai\">Rell's Ferromancy: Crash Down</span>.",
      "leveling": [
        "{{st|Shield|{{ap|40 to 160}} {{as|(+ 13% of '''maximum''' health)}}}}",
        "{{st|Increased Movement Speed|{{ap|25 to 45}}%}}",
        "{{st|Bonus Magic Damage|{{ap|10 to 70}} {{as|(+ 40% AP)}}}}"
      ],
      "notes": "* '''Rell''' will always respawn and start the game as mounted.\n* The basic attack reset is not considered one for {{ri|Hail of Blades}}.\n* '''Rell''' can use the empowered attack even while {{tip|ground|grounded}} or {{tip|root|rooted}}.\n* The {{tip|dash}} can be {{tip|knockdown|knocked down}} but the attack's effects will still be applied.\n* {{tip|Displacement immunity}} will not resist the application of the {{tip|stun}}.\n* If the target becomes {{tip|untargetable}}, {{tip|death|dies}}, or is too far away or no longer in {{tip|sight}} during the empowered attack's cast time, it is cancelled but not consumed.",
      "skillkey": "W",
      "skillid": "w2",
      "cost_warn": "Wiki's and Riot's mana costs do not match: Wiki's value  0 as 0 and riot's value 40,40,40,40,40 as 40",
      "effects": [
        {
          "str": "<ul class=\"st\"><li><span class=\"blue\">Shield</span>: <span><SpellSpan :list=\"[40,70,100,130,160]\"></SpellSpan> <span class=\"health\">(+ 13% of <b>maximum</b> health)</span></span></li></ul>",
          "vars": {
            "as_ratios": [
              {
                "player_total_hp": 0.13
              }
            ],
            "st_slices": [
              [
                "Shield",
                "<SpellSpan :list=\"[40,70,100,130,160]\"></SpellSpan> <span class=\"health\">(+ 13% of <b>maximum</b> health)</span>"
              ]
            ],
            "ap_progressions": [
              [
                40,
                70,
                100,
                130,
                160
              ]
            ]
          },
          "subeffects": [
            {
              "index": 0,
              "title": "Shield",
              "damage_type": "magic",
              "ratios": {
                "base_damage": [
                  40,
                  70,
                  100,
                  130,
                  160
                ],
                "player_total_hp": 0.13
              }
            }
          ]
        },
        {
          "str": "<ul class=\"st\"><li><span class=\"blue\">Increased Movement Speed</span>: <span><SpellSpan :list=\"[25,30,35,40,45]\"></SpellSpan>%</span></li></ul>",
          "vars": {
            "as_ratios": [],
            "st_slices": [
              [
                "Increased Movement Speed",
                "<SpellSpan :list=\"[25,30,35,40,45]\"></SpellSpan>%"
              ]
            ],
            "ap_progressions": [
              [
                25,
                30,
                35,
                40,
                45
              ]
            ]
          },
          "subeffects": [
            {
              "index": 0,
              "title": "Increased Movement Speed",
              "damage_type": "magic",
              "ratios": {
                "base_damage": [
                  25,
                  30,
                  35,
                  40,
                  45
                ]
              }
            }
          ]
        },
        {
          "str": "<ul class=\"st\"><li><span class=\"blue\">Bonus Magic Damage</span>: <span><SpellSpan :list=\"[10,25,40,55,70]\"></SpellSpan> <span class=\"ap\">(+ 40% AP)</span></span></li></ul>",
          "vars": {
            "as_ratios": [
              {
                "player_total_ap": 0.4
              }
            ],
            "st_slices": [
              [
                "Bonus Magic Damage",
                "<SpellSpan :list=\"[10,25,40,55,70]\"></SpellSpan> <span class=\"ap\">(+ 40% AP)</span>"
              ]
            ],
            "ap_progressions": [
              [
                10,
                25,
                40,
                55,
                70
              ]
            ]
          },
          "subeffects": [
            {
              "index": 0,
              "title": "Bonus Magic Damage",
              "damage_type": "magic",
              "ratios": {
                "base_damage": [
                  10,
                  25,
                  40,
                  55,
                  70
                ],
                "player_total_ap": 0.4
              }
            }
          ]
        }
      ]
    },
    "e1": {
      "riotId": "RellE",
      "name": "Attract_and_Repel",
      "maxrank": 5,
      "cooldown": [
        18,
        16.25,
        14.5,
        12.75,
        11
      ],
      "cost": 40,
      "costtype": "Mana",
      "targeting": "[[Unit-targeted|Unit]] / [[Auto-targeted|Auto]]",
      "image": {
        "full": "RellE.png",
        "sprite": "spell10.png",
        "group": "spell",
        "x": 288,
        "y": 0,
        "w": 48,
        "h": 48
      },
      "description": [
        "{{sbc|Passive:}} '''Rell''' forms a {{tip|tether}} between her and the ally bound by ''Attract and Repel'', granting the ally {{as|10% of her '''total''' armor}} and {{as|10% of her '''total''' magic resistance}} while they are nearby.",
        "{{sbc|Active:}} '''Rell''' magnetically binds herself and the allied champion nearest to the cursor with ''Attract and Repel''. '''Rell''' can then recast ''Attract and Repel'' while the tether persists.",
        "{{sbc|Recast:}} '''Rell''' erupts the tether, dealing {{as|magic damage}} to and {{tip|stun|stunning}} all enemies between and around her and the bound ally for {{fd|0.5}} seconds.",
        "'''Rell''' can [[Unit-targeted|self-target]] to dispel the current bind if she and her bound ally are not near enemy champions, and if she has not casted an [[champion ability|ability]] nor taken damage from or attacked enemy champions within the last 3 seconds. Only one ally can be bound at a time, and selecting a new ally overrides the previous bind.<br />''Attract and Repel'' will incur a {{fd|2.75}}-second {{sti|cooldown}} with no cost if '''Rell''' binds to an ally and a 1-second cooldown with no cost if she self-targets."
      ],
      "descriptionHtml": "<span class=\"sbc\">Passive:</span> <b>Rell</b> forms a <HtmlTooltip class=\"blue link\">tether<template #content><div><h4>tether<hr></h4><p>Description for keyword tether</p></div></template></HtmlTooltip> between her and the ally bound by <i>Attract and Repel</i>, granting the ally <span class=\"armor\">10% of her <b>total</b> armor</span> and <span class=\"magic-resist\">10% of her <b>total</b> magic resistance</span> while they are nearby.<br /><span class=\"sbc\">Active:</span> <b>Rell</b> magnetically binds herself and the allied champion nearest to the cursor with <i>Attract and Repel</i>. <b>Rell</b> can then recast <i>Attract and Repel</i> while the tether persists.<br /><span class=\"sbc\">Recast:</span> <b>Rell</b> erupts the tether, dealing <span class=\"magic-damage\">magic damage</span> to and <HtmlTooltip class=\"blue link\">stunning<template #content><div><h4>Stun<hr></h4><p>Unit is unable to control its movement, declare attacks, cast abilities, activate items, or use the summoner <b>Flash</b> and <b>Teleport</b> for the duration.<br><br>\nInterrupts all channeled and charged abilities<br>\nDuration reduced by <b>Tenacity</b>.<br>\nResisted by Spell and Crowd Control Immunity.<br>\nRemoved by <b>Cleanse</b>, <b>Quicksilver</b>, <b>Mikael's Crucible</b><br></p></div></template></HtmlTooltip> all enemies between and around her and the bound ally for <span style=\"font-variant-numeric: tabular-nums;\">0.5</span> seconds.<br /><b>Rell</b> can <a class=\"effect link\" title=\"self-target\">Unit-targeted</a> to dispel the current bind if she and her bound ally are not near enemy champions, and if she has not casted an <a class=\"effect link\" title=\"ability\">champion ability</a> nor taken damage from or attacked enemy champions within the last 3 seconds. Only one ally can be bound at a time, and selecting a new ally overrides the previous bind.<br /><i>Attract and Repel</i> will incur a <span style=\"font-variant-numeric: tabular-nums;\">2.75</span>-second <span>cooldown</span> with no cost if <b>Rell</b> binds to an ally and a 1-second cooldown with no cost if she self-targets.",
      "leveling": [
        "{{st|Magic Damage|{{ap|80 to 240}} {{as|(+ 30% AP)}}}}"
      ],
      "notes": "* The effects render before the cast time.\n* All units can see the effective area of the tether. Both conduits can see the tether range when within 600 units of it.\n* ''Attract and Repel'' can be cast on allies even if they are {{tip|untargetable}}.\n** '''Rell''' has an arrow indicator that points to the other conduit. Depending on the distance it glows <span style=\"color:blue;\">blue</span> (0–900), <span style=\"color:yellow;\">yellow</span> (900–2020), and <span style=\"color:red;\">red</span> (2020+)\n* ''Attract and Repel'' will be placed on a very short cooldown (less than {{fd|0.1}} seconds) when the tether is reapplied to the bound ally after the two become in tether range again.\n* Rell immediately unbinds from tethered allies when they or she dies.\n* Rell cannot begin, end, or erupt a tether by using the Self-Cast hotkey.",
      "skillkey": "E",
      "skillid": "e1",
      "effects": [
        {
          "str": "<ul class=\"st\"><li><span class=\"blue\">Magic Damage</span>: <span><SpellSpan :list=\"[80,120,160,200,240]\"></SpellSpan> <span class=\"ap\">(+ 30% AP)</span></span></li></ul>",
          "vars": {
            "as_ratios": [
              {
                "player_total_ap": 0.3
              }
            ],
            "st_slices": [
              [
                "Magic Damage",
                "<SpellSpan :list=\"[80,120,160,200,240]\"></SpellSpan> <span class=\"ap\">(+ 30% AP)</span>"
              ]
            ],
            "ap_progressions": [
              [
                80,
                120,
                160,
                200,
                240
              ]
            ]
          },
          "subeffects": [
            {
              "index": 0,
              "title": "Magic Damage",
              "damage_type": "magic",
              "ratios": {
                "base_damage": [
                  80,
                  120,
                  160,
                  200,
                  240
                ],
                "player_total_ap": 0.3
              }
            }
          ]
        }
      ]
    },
    "r1": {
      "riotId": "RellR",
      "name": "Magnet_Storm",
      "maxrank": 3,
      "cooldown": [
        120,
        100,
        80
      ],
      "cost": 100,
      "costtype": "Mana",
      "targeting": "Auto",
      "image": {
        "full": "RellR.png",
        "sprite": "spell10.png",
        "group": "spell",
        "x": 336,
        "y": 0,
        "w": 48,
        "h": 48
      },
      "description": [
        "{{sbc|Active:}} '''Rell''' erupts with magnetic fury, {{tip|airborne|pulling}} all nearby enemies {{tt|towards her|to a ring 225 units around Rell, but minimum 100 pull distance}} and creating a field of gravitational force around her for the next 2 seconds that deals {{as|magic damage}} every {{fd|0.25}} seconds to nearby enemies and continuously {{tip|kinematics|drags}} them towards her."
      ],
      "descriptionHtml": "<span class=\"sbc\">Active:</span> <b>Rell</b> erupts with magnetic fury, <HtmlTooltip class=\"blue link\">pulling<template #content><div><h4>airborne<hr></h4><p>Description for keyword airborne</p></div></template></HtmlTooltip> all nearby enemies <span class=\"title-tooltip\" title=\"to a ring 225 units around Rell, but minimum 100 pull distance\">towards her</span> and creating a field of gravitational force around her for the next 2 seconds that deals <span class=\"magic-damage\">magic damage</span> every <span style=\"font-variant-numeric: tabular-nums;\">0.25</span> seconds to nearby enemies and continuously <HtmlTooltip class=\"blue link\">drags<template #content><div><h4>kinematics<hr></h4><p>Description for keyword kinematics</p></div></template></HtmlTooltip> them towards her.",
      "leveling": [
        "{{st|Magic Damage Per Tick|{{ap|15 to 35}} {{as|(+ {{fd|13.75}}% AP)}}|Total Magic Damage Per Target|{{ap|120 to 280}} {{as|(+ 110% AP)}}}}"
      ],
      "notes": "{{Effect at cast time end}}\n* Enemies that leave the field can still be dragged after entering the corresponding area again.\n* ''Magnet Storm'' will '''not''' drag units that are:\n** {{tip|Dash|Dashing}}.\n** Being displaced (e.g. by {{tip|airborne}} effects or via abilities such as {{ai|Impale|Skarner}}).\n** {{tip|Attach|Attached}}.\n** {{tip|Displacement immune|Displacement immune}}.\n** {{tip|cc-immune|Immune to crowd control}}.\n* {{tip|Spell shield}} will block the initial {{tip|airborne|pull}} but not the dragging effect.",
      "skillkey": "R",
      "skillid": "r1",
      "effects": [
        {
          "str": "<ul class=\"st\"><li><span class=\"blue\">Magic Damage Per Tick</span>: <span><SpellSpan :list=\"[15,25,35]\"></SpellSpan> <span class=\"ap\">(+ <span style=\"font-variant-numeric: tabular-nums;\">13.75</span>% AP)</span></span></li><li><span class=\"blue\">Total Magic Damage Per Target</span>: <span><SpellSpan :list=\"[120,200,280]\"></SpellSpan> <span class=\"ap\">(+ 110% AP)</span></span></li></ul>",
          "vars": {
            "as_ratios": [
              {
                "player_total_ap": 1.1
              },
              {
                "player_total_ap": 0.1375
              }
            ],
            "st_slices": [
              [
                "Magic Damage Per Tick",
                "<SpellSpan :list=\"[15,25,35]\"></SpellSpan> <span class=\"ap\">(+ <span style=\"font-variant-numeric: tabular-nums;\">13.75</span>% AP)</span>",
                "Total Magic Damage Per Target",
                "<SpellSpan :list=\"[120,200,280]\"></SpellSpan> <span class=\"ap\">(+ 110% AP)</span>"
              ]
            ],
            "ap_progressions": [
              [
                15,
                25,
                35
              ],
              [
                120,
                200,
                280
              ]
            ]
          },
          "subeffects": [
            {
              "index": 0,
              "title": "Magic Damage Per Tick",
              "damage_type": "magic",
              "ratios": {
                "base_damage": [
                  15,
                  25,
                  35
                ],
                "player_total_ap": 0.1375
              }
            }
          ]
        }
      ]
    }
  }
}